{
    "model": "Cascadia_ANT+RF_Delph2018",
    "geospatial_lon_min": -124.8,
    "geospatial_lon_max": -120.0,
    "geospatial_lat_min": 40.0,
    "geospatial_lat_max": 49.0,
    "geospatial_vertical_min": -3.0,
    "geospatial_vertical_max": 80.0,
    "geospatial_vertical_units": "km",
    "num_images": 27,
    "dir_name": "/static/images/Cascadia_vs_depth_slice_altered_bias_scale/",
    "img_stem": "Cascadia_vs_slice-",
    "lon_axis_num_images": 47,
    "lon_axis_dir_name": "/static/images/Cascadia_vs_y_axis_slice_altered_bias_scale2/",
    "lon_axis_img_stem": "Cascadia_vs_slice-",
    "lat_axis_num_images": 86,
    "lat_axis_dir_name": "/static/images/Cascadia_vs_z_axis_slice_altered_bias_scale/",
    "lat_axis_img_stem": "Cascadia_vs_slice-"
}
